eshaansmart/__init__.py
eshaansmart/setup.py
eshaansmart-3.0.0.dist-info/METADATA
eshaansmart-3.0.0.dist-info/WHEEL
eshaansmart-3.0.0.dist-info/top_level.txt
eshaansmart-3.0.0.dist-info/RECORD
